sentry_dynamic_sampling_lib/__init__.py
sentry_dynamic_sampling_lib/sampler.py
sentry_dynamic_sampling_lib/settings.py
sentry_dynamic_sampling_lib/shared.py
sentry_dynamic_sampling_lib/utils.py
sentry_dynamic_sampling_lib-1.2.0.dist-info/LICENSE
sentry_dynamic_sampling_lib-1.2.0.dist-info/WHEEL
sentry_dynamic_sampling_lib-1.2.0.dist-info/METADATA
sentry_dynamic_sampling_lib-1.2.0.dist-info/RECORD
