Metadata-Version: 2.1
Name: sentry-dynamic-sampling-lib
Version: 1.2.0
Summary: This project aims to provide dynamic sampling without relying on Sentry Dynamic Sampling.
Home-page: https://github.com/SpikeeLabs/django-admin-action-tools
License: BSD-2-Clause
Author: jeanloup.monnier
Author-email: jean-loup.monnier@spikeelabs.fr
Maintainer: jeanloup.monnier
Maintainer-email: jean-loup.monnier@spikeelabs.fr
Requires-Python: >=3.8,<4.0
Classifier: License :: OSI Approved :: BSD License
Classifier: Programming Language :: Python :: 3
Classifier: Programming Language :: Python :: 3.8
Classifier: Programming Language :: Python :: 3.9
Classifier: Programming Language :: Python :: 3.10
Classifier: Programming Language :: Python :: 3.11
Classifier: Programming Language :: Python :: 3 :: Only
Classifier: Programming Language :: Python :: 3.10
Classifier: Programming Language :: Python :: 3.11
Classifier: Programming Language :: Python :: 3.8
Classifier: Programming Language :: Python :: 3.9
Requires-Dist: psutil (>=5.9.4,<6.0.0)
Requires-Dist: requests-cache (>=0.9.7,<0.10.0)
Requires-Dist: schedule (>=1.1.0,<2.0.0)
Requires-Dist: wrapt (>=1.14.1,<2.0.0)
Project-URL: Repository, https://github.com/SpikeeLabs/django-admin-action-tools
